pii_generator/BaltimoreCyberTrustRoot.crt.pem
pii_generator/__init__.py
pii_generator/azure_sql.py
pii_generator/card_generator.py
pii_generator/command_line.py
pii_generator/constants.py
pii_generator/gcp_bigquery.py
pii_generator/gcp_mysql.py
pii_generator/gcp_psql.py
pii_generator/gcp_sql.py
pii_generator/maria.py
pii_generator/mongo_docs.py
pii_generator/mysql_config.py
pii_generator/pii_data_generator.py
pii_generator/production_config.py
pii_generator/psql_config.py
pii_generator/sql_config.py
pii_generator/test.py
pii_generator/utils.py
pii_data_generator-1.1.2.dist-info/LICENSE
pii_data_generator-1.1.2.dist-info/METADATA
pii_data_generator-1.1.2.dist-info/WHEEL
pii_data_generator-1.1.2.dist-info/entry_points.txt
pii_data_generator-1.1.2.dist-info/top_level.txt
pii_data_generator-1.1.2.dist-info/RECORD
