Metadata-Version: 2.1
Name: pii-data-generator
Version: 1.1.2
Summary: It generats the dummy 'Personally identifiable information' data
Home-page: https://github.com/AvinashRajPurohit/pii-data-generator
Author: Deepak Rajpurohit
Author-email: deepakrajpurohit945@gmail.com
License: MIT
Platform: UNKNOWN
Classifier: License :: OSI Approved :: MIT License
Classifier: Programming Language :: Python :: 3.6
Classifier: Programming Language :: Python :: 3.7
Classifier: Programming Language :: Python :: 3.8
Classifier: Programming Language :: Python :: 3.9
License-File: LICENSE
Requires-Dist: asn1crypto (==1.4.0)
Requires-Dist: bleach (==4.1.0)
Requires-Dist: cachetools (==4.2.4)
Requires-Dist: certifi (==2021.10.8)
Requires-Dist: charset-normalizer (==2.0.8)
Requires-Dist: colorama (==0.4.4)
Requires-Dist: docutils (==0.18.1)
Requires-Dist: Faker (==9.8.3)
Requires-Dist: google-api-core (==2.2.2)
Requires-Dist: google-api-python-client (==2.32.0)
Requires-Dist: google-auth (==2.3.3)
Requires-Dist: google-auth-httplib2 (==0.1.0)
Requires-Dist: google-cloud (==0.34.0)
Requires-Dist: google-cloud-bigquery (==2.31.0)
Requires-Dist: google-cloud-core (==2.2.1)
Requires-Dist: google-crc32c (==1.3.0)
Requires-Dist: google-resumable-media (==2.1.0)
Requires-Dist: googleapis-common-protos (==1.53.0)
Requires-Dist: grpcio (==1.42.0)
Requires-Dist: grpcio-status (==1.42.0)
Requires-Dist: httplib2 (==0.20.2)
Requires-Dist: idna (==3.3)
Requires-Dist: importlib-metadata (==4.8.2)
Requires-Dist: keyring (==23.4.0)
Requires-Dist: mongoengine (==0.23.1)
Requires-Dist: mysql-connector (==2.2.9)
Requires-Dist: mysql-connector-python (==8.0.27)
Requires-Dist: numpy (==1.21.4)
Requires-Dist: packaging (==21.3)
Requires-Dist: pandas (==1.3.4)
Requires-Dist: pg8000 (==1.23.0)
Requires-Dist: pkginfo (==1.8.1)
Requires-Dist: proto-plus (==1.19.8)
Requires-Dist: protobuf (==3.19.1)
Requires-Dist: psycopg2-binary (==2.9.2)
Requires-Dist: pyarrow (==6.0.1)
Requires-Dist: pyasn1 (==0.4.8)
Requires-Dist: pyasn1-modules (==0.2.8)
Requires-Dist: pydantic (==1.8.2)
Requires-Dist: Pygments (==2.10.0)
Requires-Dist: pymongo (==3.12.1)
Requires-Dist: pyparsing (==3.0.6)
Requires-Dist: python-dateutil (==2.8.2)
Requires-Dist: python-tds (==1.11.0)
Requires-Dist: pytz (==2021.3)
Requires-Dist: readme-renderer (==30.0)
Requires-Dist: requests (==2.26.0)
Requires-Dist: requests-toolbelt (==0.9.1)
Requires-Dist: rfc3986 (==1.5.0)
Requires-Dist: rsa (==4.8)
Requires-Dist: scramp (==1.4.1)
Requires-Dist: six (==1.16.0)
Requires-Dist: text-unidecode (==1.3)
Requires-Dist: tqdm (==4.62.3)
Requires-Dist: twine (==3.6.0)
Requires-Dist: typing-extensions (==4.0.1)
Requires-Dist: uritemplate (==4.1.1)
Requires-Dist: urllib3 (==1.26.7)
Requires-Dist: webencodings (==0.5.1)
Requires-Dist: zipp (==3.6.0)
